dddocr_py/init.py
dddocr_py/main.py
dddocr_py-0.1.0.dist-info/licenses/LICENSE
dddocr_py-0.1.0.dist-info/METADATA
dddocr_py-0.1.0.dist-info/WHEEL
dddocr_py-0.1.0.dist-info/top_level.txt
dddocr_py-0.1.0.dist-info/RECORD
